LICENSE
MANIFEST.in
README.md
README.rst
setup.py
pycompat/__init__.py
pycompat.egg-info/PKG-INFO
pycompat.egg-info/SOURCES.txt
pycompat.egg-info/dependency_links.txt
pycompat.egg-info/top_level.txt