Metadata-Version: 1.1
Name: pycompat
Version: 0.3.0
Summary: Library to check Python and System version in a easy way
Home-page: https://github.com/alexandrevicenzi/pycompat
Author: Alexandre Vicenzi
Author-email: vicenzi.alexandre@gmail.com
License: The MIT License (MIT)
